README.md
setup.py
TOPSIS_Yash_101803457.egg-info/PKG-INFO
TOPSIS_Yash_101803457.egg-info/SOURCES.txt
TOPSIS_Yash_101803457.egg-info/dependency_links.txt
TOPSIS_Yash_101803457.egg-info/top_level.txt
topsis_gen/__init__.py
topsis_gen/topsis_cal.py