Metadata-Version: 2.1
Name: TOPSIS-Yash-101803457
Version: 1.0.0
Summary: Topsis Calculator
Home-page: UNKNOWN
Author: Yash Mittal
Author-email: ymittal_be18@thapar.edu
License: UNKNOWN
Platform: UNKNOWN
Classifier: Programming Language :: Python :: 3
Classifier: License :: OSI Approved :: MIT License
Classifier: Operating System :: OS Independent
